{
  "$ref": "#/definitions/services",
  "definitions": {
    "services": {
      "type": "object",
      "properties": {
        "title": {
          "type": "string"
        },
        "description": {
          "type": "string"
        },
        "icon": {
          "type": "string"
        },
        "order": {
          "type": "number"
        },
        "lang": {
          "type": "string",
          "enum": [
            "fr",
            "en"
          ]
        },
        "$schema": {
          "type": "string"
        }
      },
      "required": [
        "title",
        "description",
        "order",
        "lang"
      ],
      "additionalProperties": false
    }
  },
  "$schema": "http://json-schema.org/draft-07/schema#"
}